zecwallet/__init__.py
zecwallet/wallet.py
zecwallet-1.5.1.dist-info/LICENSE
zecwallet-1.5.1.dist-info/METADATA
zecwallet-1.5.1.dist-info/WHEEL
zecwallet-1.5.1.dist-info/top_level.txt
zecwallet-1.5.1.dist-info/RECORD
