Metadata-Version: 2.1
Name: zecwallet
Version: 1.5.1
Summary: A wrapper around the Zecwallet Command Line LightClient
Home-page: https://github.com/P5vc/Zecwallet-Python
Author: Priveasy
Author-email: Admin@Priveasy.org
License: UNKNOWN
Platform: UNKNOWN
Classifier: Programming Language :: Python :: 3
Classifier: License :: OSI Approved :: MIT License
Classifier: Operating System :: OS Independent
Requires-Python: >=3.6
License-File: LICENSE
